pydiver/__init__.py
pydiver/util.py
pydiver-0.0.4.dist-info/METADATA
pydiver-0.0.4.dist-info/WHEEL
pydiver-0.0.4.dist-info/top_level.txt
pydiver-0.0.4.dist-info/RECORD
