Metadata-Version: 2.1
Name: pydiver
Version: 0.0.4
Summary: A pydiver package
Home-page: https://github.com/modules.py/pydiver
Author: Almos Gero
Author-email: almos.gero@gmail.com
Classifier: Programming Language :: Python :: 3
Classifier: License :: OSI Approved :: MIT License
Classifier: Operating System :: OS Independent
